odoo9_addon_web_export_view-9.0.1.0.2-py2.7-nspkg.pth
odoo9_addon_web_export_view-9.0.1.0.2.dist-info/top_level.txt
odoo9_addon_web_export_view-9.0.1.0.2.dist-info/WHEEL
odoo9_addon_web_export_view-9.0.1.0.2.dist-info/RECORD
odoo9_addon_web_export_view-9.0.1.0.2.dist-info/metadata.json
odoo9_addon_web_export_view-9.0.1.0.2.dist-info/DESCRIPTION.rst
odoo9_addon_web_export_view-9.0.1.0.2.dist-info/METADATA
odoo9_addon_web_export_view-9.0.1.0.2.dist-info/namespace_packages.txt
odoo_addons/web_export_view/__openerp__.py
odoo_addons/web_export_view/__init__.py
odoo_addons/web_export_view/README.rst
odoo_addons/web_export_view/view/web_export_view.xml
odoo_addons/web_export_view/i18n/web_export_view.pot
odoo_addons/web_export_view/i18n/is.po
odoo_addons/web_export_view/i18n/es.po
odoo_addons/web_export_view/i18n/sl.po
odoo_addons/web_export_view/i18n/nl.po
odoo_addons/web_export_view/i18n/de.po
odoo_addons/web_export_view/i18n/fr.po
odoo_addons/web_export_view/controllers/controllers.py
odoo_addons/web_export_view/controllers/__init__.py
odoo_addons/web_export_view/static/description/icon.png
odoo_addons/web_export_view/static/src/js/web_export_view.js
